AUTHORS
LICENSE.rst
MANIFEST.in
README.md
requirements-dev.txt
requirements-setup.txt
setup.py
nonprimary_foreignkey/__init__.py
nonprimary_foreignkey/fields.py
nonprimary_foreignkey.egg-info/PKG-INFO
nonprimary_foreignkey.egg-info/SOURCES.txt
nonprimary_foreignkey.egg-info/dependency_links.txt
nonprimary_foreignkey.egg-info/requires.txt
nonprimary_foreignkey.egg-info/top_level.txt