Metadata-Version: 1.1
Name: nonprimary-foreignkey
Version: 0.0.0
Summary: Allows foreign-key prefetches on non-primary-key fields
Home-page: https://github.com/lucaswiman/nonprimary-foreignkey
Author: Lucas Wiman
Author-email: lucas.wiman@gmail.com
License: Apache 2.0
Platform: UNKNOWN
Classifier: Topic :: Internet :: WWW/HTTP :: Dynamic Content
Classifier: Intended Audience :: Developers
Classifier: Programming Language :: Python
Classifier: Programming Language :: Python :: 2
Classifier: Programming Language :: Python :: 2.7
Classifier: Programming Language :: Python :: 3
Classifier: Programming Language :: Python :: 3.4
Classifier: Framework :: Django
Classifier: Development Status :: 4 - Beta
Classifier: Operating System :: OS Independent
